txtmuch/__init__.py
txtmuch/core.py
txtmuch/utils.py
txtmuch-0.1.1.dist-info/METADATA
txtmuch-0.1.1.dist-info/WHEEL
txtmuch-0.1.1.dist-info/top_level.txt
txtmuch-0.1.1.dist-info/RECORD
