Metadata-Version: 2.1
Name: txtmuch
Version: 0.1.1
Summary: A txt model,it is my first model,use for test.
Home-page: https://github.com/theoyu314159/txtmuch/tree/main
Author: theoyu314159
Author-email: sladersyuyu@gmail.com
Classifier: Programming Language :: Python :: 3
Classifier: License :: OSI Approved :: MIT License
Classifier: Operating System :: OS Independent
Requires-Python: >=3.6
